{
  "$schema": "https://developer.microsoft.com/json-schemas/fabric/item/report/definition/visual/1.2.0/schema.json",
  "name": "537ac805fa8442b0b48d",
  "visual": {
    "visualType": "clusteredColumnChart",
    "objects": {
      "title": [
        {
          "properties": {
            "text": {
              "expr": {
                "Literal": {
                  "Value": "'CommissionProjection'"
                }
              }
            },
            "show": {
              "expr": {
                "Literal": {
                  "Value": "true"
                }
              }
            }
          }
        }
      ]
    },
    "visualContainerObjects": {
      "background": [
        {
          "properties": {
            "show": {
              "expr": {
                "Literal": {
                  "Value": "true"
                }
              }
            }
          }
        }
      ]
    }
  },
  "position": {
    "x": 0,
    "y": 526,
    "z": 0,
    "width": 1280,
    "height": 100
  }
}